{
	"format_version": "1.12.0",
	"minecraft:geometry": [
		{
			"description": {
				"identifier": "geometry.moonrose",
				"texture_width": 256,
				"texture_height": 256,
				"visible_bounds_width": 4,
				"visible_bounds_height": 5.5,
				"visible_bounds_offset": [0, 2.25, 0]
			},
			"bones": [
				{
					"name": "flower",
					"pivot": [0, 0, 0]
				},
				{
					"name": "fullbody",
					"parent": "flower",
					"pivot": [0, 0, 0]
				},
				{
					"name": "vine",
					"parent": "fullbody",
					"pivot": [0, 0, 0]
				},
				{
					"name": "bone",
					"parent": "vine",
					"pivot": [0, 0, 0],
					"cubes": [
						{"origin": [-7, 0, -7], "size": [14, 5, 14], "uv": [0, 27]}
					]
				},
				{
					"name": "bone2",
					"parent": "vine",
					"pivot": [0, 7.6, 0.5],
					"cubes": [
						{"origin": [-6, 4.1, -5.5], "size": [12, 7, 12], "pivot": [0, 7.6, 0.5], "rotation": [-7.5, 0, 0], "uv": [43, 15]}
					]
				},
				{
					"name": "bone13",
					"parent": "bone2",
					"pivot": [-0.77479, 8.81596, 8.20247],
					"cubes": [
						{"origin": [0.14843, 7.7335, -8.13591], "size": [2, 2, 2], "pivot": [0.22521, 8.81596, -7.10247], "rotation": [-90, -82.5, 90], "uv": [103, 118]},
						{"origin": [-2.69802, 8.39843, -7.56902], "size": [4, 1, 1], "pivot": [0.22521, 8.81596, -7.10247], "rotation": [-90, -82.5, 90], "uv": [119, 30]},
						{"origin": [-0.85157, 7.7335, 7.23591], "size": [2, 2, 2], "pivot": [-0.77479, 8.81596, 8.20247], "rotation": [90, 82.5, 90], "uv": [96, 5]},
						{"origin": [-3.69802, 8.39843, 7.66902], "size": [4, 1, 1], "pivot": [-0.77479, 8.81596, 8.20247], "rotation": [90, 82.5, 90], "uv": [63, 91]}
					]
				},
				{
					"name": "bone33",
					"parent": "bone2",
					"pivot": [8.47521, 8.28333, -0.10461],
					"cubes": [
						{"origin": [8.14843, 7.20087, -1.13805], "size": [3, 2, 2], "pivot": [8.47521, 8.28333, -0.10461], "rotation": [-153.73035, -0.69873, -179.9105], "uv": [113, 25]},
						{"origin": [5.30198, 7.8658, -0.57116], "size": [4, 1, 1], "pivot": [8.47521, 8.28333, -0.10461], "rotation": [-153.73035, -0.69873, -179.9105], "uv": [13, 118]}
					]
				},
				{
					"name": "bone32",
					"parent": "bone2",
					"pivot": [-7.47521, 8.28333, 0.64539],
					"cubes": [
						{"origin": [-10.14843, 7.20087, -0.38805], "size": [3, 2, 2], "pivot": [-7.47521, 8.28333, 0.64539], "rotation": [-151.75242, 20.75675, -169.65386], "uv": [113, 100]},
						{"origin": [-8.30198, 7.8658, 0.17884], "size": [4, 1, 1], "pivot": [-7.47521, 8.28333, 0.64539], "rotation": [-151.75242, 20.75675, -169.65386], "uv": [24, 118]}
					]
				},
				{
					"name": "bone3",
					"parent": "vine",
					"pivot": [0, 14.28584, 1.82895],
					"cubes": [
						{"origin": [-5, 10.28584, -3.17105], "size": [10, 8, 10], "pivot": [0, 14.28584, 1.82895], "rotation": [-15, 0, 0], "uv": [75, 68]}
					]
				},
				{
					"name": "bone14",
					"parent": "bone3",
					"pivot": [2.52479, 14.78333, 9.85461],
					"cubes": [
						{"origin": [1.14843, 16.20087, -5.88805], "size": [3, 2, 2], "pivot": [1.47521, 17.28333, -4.85461], "rotation": [-72.5, -60, 90], "uv": [116, 82]},
						{"origin": [-1.69802, 16.8658, -5.32116], "size": [4, 1, 1], "pivot": [1.47521, 17.28333, -4.85461], "rotation": [-72.5, -60, 90], "uv": [92, 118]},
						{"origin": [-0.14843, 13.70087, 8.88805], "size": [3, 2, 2], "pivot": [2.52479, 14.78333, 9.85461], "rotation": [-121.86307, -82.82277, 107.72272], "uv": [71, 114]},
						{"origin": [1.69802, 14.3658, 9.32116], "size": [4, 1, 1], "pivot": [2.52479, 14.78333, 9.85461], "rotation": [-121.86307, -82.82277, 107.72272], "uv": [35, 118]}
					]
				},
				{
					"name": "bone30",
					"parent": "bone3",
					"pivot": [6.47521, 17.28333, 2.64539],
					"cubes": [
						{"origin": [6.14843, 16.20087, 1.61195], "size": [3, 2, 2], "pivot": [6.47521, 17.28333, 2.64539], "rotation": [-155.90659, 15.88075, 174.08816], "uv": [116, 77]},
						{"origin": [3.30198, 16.8658, 2.17884], "size": [4, 1, 1], "pivot": [6.47521, 17.28333, 2.64539], "rotation": [-155.90659, 15.88075, 174.08816], "uv": [118, 67]}
					]
				},
				{
					"name": "bone31",
					"parent": "bone3",
					"pivot": [-6.47521, 15.28333, 2.64539],
					"cubes": [
						{"origin": [-9.14843, 14.20087, 1.61195], "size": [3, 2, 2], "pivot": [-6.47521, 15.28333, 2.64539], "rotation": [-153.25026, -10.49594, 174.31957], "uv": [113, 115]},
						{"origin": [-7.30198, 14.8658, 2.17884], "size": [4, 1, 1], "pivot": [-6.47521, 15.28333, 2.64539], "rotation": [-153.25026, -10.49594, 174.31957], "uv": [118, 39]}
					]
				},
				{
					"name": "bone4",
					"parent": "vine",
					"pivot": [0.5, 19.50478, 4.49619],
					"cubes": [
						{"origin": [-4.5, 15.50478, -0.50381], "size": [9, 13, 9], "inflate": -0.1, "pivot": [0.5, 19.50478, 4.49619], "rotation": [-37.5, 0, 0], "uv": [38, 68]}
					]
				},
				{
					"name": "bone27",
					"parent": "bone4",
					"pivot": [-6.52479, 22.53333, 5.89539],
					"cubes": [
						{"origin": [-6.85157, 21.45087, 4.86195], "size": [3, 2, 2], "pivot": [-6.52479, 22.53333, 5.89539], "rotation": [-24.43103, -6.6847, 6.952], "uv": [113, 110]},
						{"origin": [-8.69802, 22.1158, 5.42884], "size": [3, 1, 1], "pivot": [-6.52479, 22.53333, 5.89539], "rotation": [-24.43103, -6.6847, 6.952], "uv": [120, 62]}
					]
				},
				{
					"name": "bone29",
					"parent": "bone4",
					"pivot": [0.47521, 20.28333, 12.60461],
					"cubes": [
						{"origin": [0.14843, 19.20087, 11.63805], "size": [3, 2, 2], "pivot": [0.47521, 20.28333, 12.60461], "rotation": [-50.02613, 47.0802, -53.75238], "uv": [82, 114]},
						{"origin": [-1.69802, 19.8658, 12.07116], "size": [3, 1, 1], "pivot": [0.47521, 20.28333, 12.60461], "rotation": [-50.02613, 47.0802, -53.75238], "uv": [120, 92]}
					]
				},
				{
					"name": "bone28",
					"parent": "bone4",
					"pivot": [6.52479, 22.53333, 6.89539],
					"cubes": [
						{"origin": [3.85157, 21.45087, 5.86195], "size": [3, 2, 2], "pivot": [6.52479, 22.53333, 6.89539], "rotation": [-24.44736, -6.98464, -0.76077], "uv": [113, 105]},
						{"origin": [5.69802, 22.1158, 6.42884], "size": [3, 1, 1], "pivot": [6.52479, 22.53333, 6.89539], "rotation": [-24.44736, -6.98464, -0.76077], "uv": [80, 119]}
					]
				},
				{
					"name": "bone15",
					"parent": "bone4",
					"pivot": [-1.52479, 24.28333, 0.14539],
					"cubes": [
						{"origin": [-1.85157, 23.20087, -0.88805], "size": [3, 2, 2], "pivot": [-1.52479, 24.28333, 0.14539], "rotation": [-47.46584, -49.67393, 59.73157], "uv": [115, 42]},
						{"origin": [-3.69802, 23.8658, -0.32116], "size": [3, 1, 1], "pivot": [-1.52479, 24.28333, 0.14539], "rotation": [-47.46584, -49.67393, 59.73157], "uv": [120, 95]}
					]
				},
				{
					"name": "bone5",
					"parent": "vine",
					"pivot": [-0.5, 31.65744, 10.99647],
					"cubes": [
						{"origin": [-4, 25.15744, 7.49647], "size": [8, 7, 8], "inflate": -0.2, "pivot": [-0.5, 31.65744, 10.99647], "rotation": [-22.5, 0, 0], "uv": [80, 10]}
					]
				},
				{
					"name": "bone6",
					"parent": "vine",
					"pivot": [0, 35.17201, 12.09649],
					"cubes": [
						{"origin": [-4, 30.67201, 8.09649], "size": [8, 6, 8], "inflate": -0.21, "pivot": [0, 35.17201, 12.09649], "rotation": [-10, 0, 0], "uv": [67, 87]}
					]
				},
				{
					"name": "bone16",
					"parent": "bone6",
					"pivot": [-0.52479, 29.28333, 16.60461],
					"cubes": [
						{"origin": [-0.85157, 32.20087, 6.11195], "size": [3, 2, 2], "pivot": [-0.52479, 33.28333, 7.14539], "rotation": [-23.18312, -61.58119, 30.6643], "uv": [113, 20]},
						{"origin": [-2.69802, 32.8658, 6.67884], "size": [3, 1, 1], "pivot": [-0.52479, 33.28333, 7.14539], "rotation": [-23.18312, -61.58119, 30.6643], "uv": [44, 120]},
						{"origin": [-0.85157, 28.20087, 15.63805], "size": [3, 2, 2], "pivot": [-0.52479, 29.28333, 16.60461], "rotation": [-32.38675, 58.79724, -31.85813], "uv": [41, 106]},
						{"origin": [-1.69802, 28.8658, 16.07116], "size": [2, 1, 1], "pivot": [-0.52479, 29.28333, 16.60461], "rotation": [-32.38675, 58.79724, -31.85813], "uv": [87, 102]}
					]
				},
				{
					"name": "bone17",
					"parent": "bone6",
					"pivot": [3.77479, 40.53333, 11.85461],
					"cubes": [
						{"origin": [-5.10157, 30.45087, 9.88805], "size": [3, 2, 2], "pivot": [-4.77479, 31.53333, 10.85461], "rotation": [-13.75772, -9.62107, -21.56354], "uv": [19, 104]},
						{"origin": [-5.94802, 31.1158, 10.32116], "size": [2, 1, 1], "pivot": [-4.77479, 31.53333, 10.85461], "rotation": [-13.75772, -9.62107, -21.56354], "uv": [29, 94]}
					]
				},
				{
					"name": "bone26",
					"parent": "bone17",
					"pivot": [4.77479, 33.53333, 11.85461],
					"cubes": [
						{"origin": [3.94802, 33.1158, 11.32116], "size": [2, 1, 1], "pivot": [4.77479, 33.53333, 11.85461], "rotation": [-16.7249, -0.58117, -14.68766], "uv": [92, 26]},
						{"origin": [2.10157, 32.45087, 10.88805], "size": [3, 2, 2], "pivot": [4.77479, 33.53333, 11.85461], "rotation": [-16.7249, -0.58117, -14.68766], "uv": [41, 47]}
					]
				},
				{
					"name": "bone7",
					"parent": "vine",
					"pivot": [-0.5, 38.15154, 11.73168],
					"cubes": [
						{"origin": [-3.5, 35.15154, 8.73168], "size": [7, 7, 7], "inflate": -0.3, "pivot": [-0.5, 38.15154, 11.73168], "rotation": [5, 0, 0], "uv": [29, 91]}
					]
				},
				{
					"name": "bone18",
					"parent": "bone7",
					"pivot": [3.77479, 40.53333, 11.85461],
					"cubes": [
						{"origin": [2.94802, 40.1158, 11.32116], "size": [2, 1, 1], "pivot": [3.77479, 40.53333, 11.85461], "rotation": [18.2751, -0.58117, -14.68766], "uv": [92, 29]}
					]
				},
				{
					"name": "bone22",
					"parent": "bone7",
					"pivot": [-0.52479, 42.28333, 15.10461],
					"cubes": [
						{"origin": [-2.69802, 41.8658, 14.57116], "size": [3, 1, 1], "pivot": [-0.52479, 42.28333, 15.10461], "rotation": [58.04297, 68.31063, 70.61997], "uv": [119, 74]}
					]
				},
				{
					"name": "bone21",
					"parent": "bone7",
					"pivot": [-3.52479, 40.53333, 12.10461],
					"cubes": [
						{"origin": [-4.69802, 40.1158, 11.57116], "size": [2, 1, 1], "pivot": [-3.52479, 40.53333, 12.10461], "rotation": [18.57047, 10.07111, 17.858], "uv": [0, 92]}
					]
				},
				{
					"name": "bone23",
					"parent": "bone7",
					"pivot": [-0.52479, 41.28333, 8.39539],
					"cubes": [
						{"origin": [-2.69802, 40.8658, 7.92884], "size": [3, 1, 1], "pivot": [-0.52479, 41.28333, 8.39539], "rotation": [54.68458, -70.22182, -45.59134], "uv": [71, 119]}
					]
				},
				{
					"name": "bone8",
					"parent": "vine",
					"pivot": [0, 43.52077, 10.77909],
					"cubes": [
						{"origin": [-3.5, 40.02077, 7.27909], "size": [7, 7, 7], "inflate": -0.31, "pivot": [0, 43.52077, 10.77909], "rotation": [27.5, 0, 0], "uv": [0, 89]}
					]
				},
				{
					"name": "bone9",
					"parent": "vine",
					"pivot": [-0.5, 48.43821, 5.32313],
					"cubes": [
						{"origin": [-3, 42.47229, 3.31363], "size": [6, 7, 6], "inflate": -0.32, "pivot": [-0.5, 48.43821, 5.32313], "rotation": [50, 0, 0], "uv": [0, 104]}
					]
				},
				{
					"name": "bone19",
					"parent": "bone9",
					"pivot": [2.77479, 49.28333, 5.60461],
					"cubes": [
						{"origin": [1.94802, 48.8658, 5.07116], "size": [2, 1, 1], "pivot": [2.77479, 49.28333, 5.60461], "rotation": [18.2751, -0.58117, -14.68766], "uv": [83, 45]}
					]
				},
				{
					"name": "bone20",
					"parent": "bone9",
					"pivot": [-2.77479, 49.28333, 4.35461],
					"cubes": [
						{"origin": [-3.94802, 48.8658, 3.82116], "size": [2, 1, 1], "pivot": [-2.77479, 49.28333, 4.35461], "rotation": [18.2751, 0.58117, 14.68766], "uv": [80, 15]}
					]
				},
				{
					"name": "bone24",
					"parent": "bone9",
					"pivot": [-0.70617, 51.30529, 6.74565],
					"cubes": [
						{"origin": [-2.20617, 50.80529, 6.24565], "size": [3, 1, 1], "pivot": [-0.70617, 51.30529, 6.74565], "rotation": [76.12503, -35.3428, -71.14901], "uv": [119, 36]}
					]
				},
				{
					"name": "bone25",
					"parent": "bone9",
					"pivot": [-0.70617, 46.80529, 3.25435],
					"cubes": [
						{"origin": [-1.20617, 46.30529, 2.75435], "size": [2, 1, 1], "pivot": [-0.70617, 46.80529, 3.25435], "rotation": [-77.17066, -28.24472, -85.43198], "uv": [0, 89]}
					]
				},
				{
					"name": "bone10",
					"parent": "vine",
					"pivot": [-0.5, 48.43821, 5.32313],
					"cubes": [
						{"origin": [-3, 47.40412, 3.31363], "size": [6, 7, 6], "inflate": -0.33, "pivot": [-0.5, 48.43821, 5.32313], "rotation": [72.5, 0, 0], "uv": [94, 26]}
					]
				},
				{
					"name": "bone11",
					"parent": "vine",
					"pivot": [0, 50.90404, -1.42121],
					"cubes": [
						{"origin": [-2.5, 47.90404, -3.92121], "size": [5, 6, 5], "inflate": -0.34, "pivot": [0, 50.90404, -1.42121], "rotation": [97.5, 0, 0], "uv": [25, 106]}
					]
				},
				{
					"name": "bone12",
					"parent": "vine",
					"pivot": [0, 49.93575, -6.34363],
					"cubes": [
						{"origin": [-2.5, 46.93575, -8.84363], "size": [5, 6, 5], "inflate": -0.35, "pivot": [0, 49.93575, -6.34363], "rotation": [105, 0, 0], "uv": [71, 102]}
					]
				},
				{
					"name": "head",
					"parent": "fullbody",
					"pivot": [0.58637, 47.41185, -17.44016],
					"cubes": [
						{"origin": [-5.5379, 41.17061, -10.70117], "size": [11, 11, 3], "inflate": -0.35, "pivot": [0.8, 47.03998, -19.35653], "rotation": [14.40379, 3.56172, 0.0109], "uv": [88, 45]},
						{"origin": [-5.97805, 40.38733, -12.65312], "size": [13, 13, 4], "inflate": -0.35, "pivot": [0.8, 47.03998, -19.35653], "rotation": [12.894, 4.01878, -22.53448], "uv": [0, 71]},
						{"origin": [-7.9702, 38.76123, -14.79193], "size": [15, 15, 5], "inflate": -0.35, "pivot": [0.8, 47.03998, -19.35653], "rotation": [15.62195, 2.56232, 22.52154], "uv": [47, 47]},
						{"origin": [-7.64673, 38.45167, -16.63886], "size": [17, 17, 6], "inflate": -0.35, "pivot": [0.8, 47.03998, -19.35653], "rotation": [12.894, 4.01878, -22.53448], "uv": [0, 47]},
						{"origin": [-1.14107, 45.28337, -26.66669], "size": [4, 4, 7], "inflate": -0.35, "pivot": [0.8, 47.03998, -19.35653], "rotation": [6.32866, 11.94414, -67.32606], "uv": [131, 0]},
						{"origin": [-0.69753, 45.80617, -29.40549], "size": [3, 3, 4], "inflate": -0.35, "pivot": [0.8, 47.03998, -19.35653], "rotation": [6.32866, 11.94414, -67.32606], "uv": [134, 3]},
						{"origin": [-0.19276, 46.39019, -32.53481], "size": [2, 2, 4], "inflate": -0.35, "pivot": [0.8, 47.03998, -19.35653], "rotation": [6.32866, 11.94414, -67.32606], "uv": [134, 3]},
						{"origin": [-8.72479, 37.43987, -18.63886], "size": [19, 19, 7], "inflate": -0.35, "pivot": [0.8, 47.03998, -19.35653], "rotation": [6.32866, 11.94414, -67.32606], "uv": [0, 0]},
						{"origin": [-11.02745, 39.4291, -18.23901], "size": [3, 15, 6], "inflate": -0.35, "pivot": [0.8, 47.03998, -19.35653], "rotation": [6.32866, 11.94414, -67.32606], "uv": [52, 100]},
						{"origin": [9.57255, 39.4291, -18.23901], "size": [3, 15, 6], "inflate": -0.35, "pivot": [0.8, 47.03998, -19.35653], "rotation": [6.32866, 11.94414, -67.32606], "uv": [94, 96]},
						{"origin": [-6.72745, 55.7291, -18.23901], "size": [15, 3, 6], "inflate": -0.35, "pivot": [0.8, 47.03998, -19.35653], "rotation": [6.32866, 11.94414, -67.32606], "uv": [57, 35]},
						{"origin": [-6.72745, 35.1291, -18.23901], "size": [15, 3, 6], "inflate": -0.35, "pivot": [0.8, 47.03998, -19.35653], "rotation": [6.32866, 11.94414, -67.32606], "uv": [53, 0]},
						{"origin": [-3.37586, 42.37838, -9.65511], "size": [9, 9, 3], "inflate": -0.35, "pivot": [0.8, 47.03998, -19.35653], "rotation": [11.32369, 3.86316, -45.08797], "uv": [105, 0]},
						{"origin": [-5.08292, 41.41614, -23.53323], "size": [11, 11, 3], "inflate": -0.35, "pivot": [0.8, 47.03998, -19.35653], "rotation": [10.63878, -3.23224, -1.49697], "uv": [88, 45]},
						{"origin": [-4.02922, 42.70413, -24.59707], "size": [9, 9, 3], "inflate": -0.35, "pivot": [0.8, 47.03998, -19.35653], "rotation": [6.56507, 13.74218, -43.51663], "uv": [105, 0]},
						{"origin": [-6.08541, 40.56535, -22.56631], "size": [13, 13, 4], "inflate": -0.35, "pivot": [0.8, 47.03998, -19.35653], "rotation": [10.20001, 5.6268, -22.20479], "uv": [0, 71]},
						{"origin": [-7.02214, 39.27922, -21.50287], "size": [15, 15, 5], "inflate": -0.35, "pivot": [0.8, 47.03998, -19.35653], "rotation": [7.87023, -11.66747, 19.56166], "uv": [47, 47]},
						{"origin": [-7.7541, 38.62969, -20.58057], "size": [17, 17, 6], "inflate": -0.35, "pivot": [0.8, 47.03998, -19.35653], "rotation": [10.20001, 5.6268, -22.20479], "uv": [0, 47]}
					]
				},
				{
					"name": "roots",
					"parent": "flower",
					"pivot": [11.93198, -0.44298, -3.1482],
					"cubes": [
						{"origin": [8.22754, -1.33835, -3.58971], "size": [3, 2, 2], "pivot": [11.12034, -0.60377, -2.60326], "rotation": [0, -2.5, 12.5], "uv": [117, 57]},
						{"origin": [-10.5633, 0.22966, 3.15164], "size": [4, 3, 2], "pivot": [-8.5633, 1.72966, 4.15164], "rotation": [0, 30, -12.5], "uv": [0, 27]},
						{"origin": [-12.30353, 0, -7.18417], "size": [5, 3, 3], "pivot": [-9.4897, 0.5, 0.32664], "rotation": [0, -22.5, -12.5], "uv": [88, 60]},
						{"origin": [-14.08486, -0.74785, -7.2373], "size": [5, 2, 2], "pivot": [-13.52523, 0.06731, -6.28259], "rotation": [0, -2.5, -12.5], "uv": [107, 87]},
						{"origin": [-16.87588, -1.03229, -6.91248], "size": [3, 1, 1], "pivot": [-15.37588, -0.53229, -6.41248], "rotation": [0, -15, -12.5], "uv": [112, 120]},
						{"origin": [-12.43088, -0.86767, 2.76346], "size": [6, 2, 2], "pivot": [-13.43088, -0.11767, 4.51346], "rotation": [0, 12.5, -12.5], "uv": [70, 10]},
						{"origin": [-14.92742, -1.01094, 6.18449], "size": [6, 1, 2], "pivot": [-13.92742, -0.51094, 7.43449], "rotation": [0, 35, -12.5], "uv": [105, 13]},
						{"origin": [-15.99344, -1.30269, 8.34717], "size": [2, 1, 1], "pivot": [-14.99344, -0.80269, 8.84717], "rotation": [0, 57.5, -12.5], "uv": [0, 3]},
						{"origin": [-4.04214, -0.49622, 10.08982], "size": [4, 3, 2], "pivot": [1.77837, 0.46348, 10.88133], "rotation": [-120.87896, -76.52685, 126.43715], "uv": [0, 33]},
						{"origin": [-6.85396, 0.22966, 5.24907], "size": [4, 3, 3], "pivot": [-4.85396, 1.72966, 7.24907], "rotation": [-33.45626, -68.73306, 36.47361], "uv": [51, 91]},
						{"origin": [-5.02577, -0.63982, 9.37408], "size": [4, 2, 2], "pivot": [-3.02577, 0.36018, 10.37408], "rotation": [-23.5021, -59.90493, 25.46735], "uv": [22, 89]},
						{"origin": [-4.069, -1.39995, 13.68898], "size": [4, 1, 1], "pivot": [-2.069, -0.39995, 13.68898], "rotation": [-64.88331, -77.24126, 69.17768], "uv": [65, 102]},
						{"origin": [-3.81979, -0.49622, 7.41947], "size": [6, 2, 2], "pivot": [1.77837, 0.46348, 10.88133], "rotation": [-48.26383, -74.45649, 52.05067], "uv": [43, 35]},
						{"origin": [2.92056, -0.70165, 11.22999], "size": [6, 1, 2], "pivot": [4.06329, -0.22871, 12.61701], "rotation": [-152.48674, 62.52169, -157.40293], "uv": [100, 40]},
						{"origin": [1.1993, -0.75576, 11.76382], "size": [2, 1, 1], "pivot": [4.06329, -0.22871, 12.61701], "rotation": [-163.45657, 41.53271, -171.06279], "uv": [0, 0]},
						{"origin": [6.4879, -0.11045, 4], "size": [4, 3, 2], "pivot": [9.9879, 0.38955, 4], "rotation": [0, -12.5, 12.5], "uv": [46, 0]},
						{"origin": [6.4879, -0.11045, 2], "size": [6, 2, 2], "pivot": [9.9879, 0.38955, 4], "rotation": [0, -12.5, 12.5], "uv": [53, 10]},
						{"origin": [7.30353, 0, -7.18417], "size": [5, 3, 3], "pivot": [9.4897, 0.5, 0.32664], "rotation": [0, 22.5, 12.5], "uv": [66, 68]},
						{"origin": [8.42438, -0.79264, -9.99499], "size": [5, 2, 2], "pivot": [13.09959, 0.02252, -8.77512], "rotation": [0, 45, 22.5], "uv": [90, 0]},
						{"origin": [12.29352, -0.94635, -10.35775], "size": [5, 1, 1], "pivot": [14.79352, -0.44635, -9.85775], "rotation": [-5.123, 21.93857, 9.0064], "uv": [106, 74]},
						{"origin": [10.62195, -1.6642, -2.30604], "size": [5, 1, 1], "pivot": [13.12195, -1.1642, -1.80604], "rotation": [0, -25, 12.5], "uv": [0, 118]},
						{"origin": [4.69383, -1.52725, -4.6609], "size": [4, 3, 3], "pivot": [11.93198, -0.44298, -3.1482], "rotation": [0, 10, 12.5], "uv": [106, 67]},
						{"origin": [6.38971, -0.44834, -14.88356], "size": [5, 1, 1], "pivot": [9.88971, 0.05166, -14.38356], "rotation": [0, 35, 12.5], "uv": [107, 97]},
						{"origin": [1.73177, 0.21484, -12.76447], "size": [4, 3, 3], "pivot": [6.69161, 1.11031, -11.30478], "rotation": [0, 75, 12.5], "uv": [105, 60]},
						{"origin": [4.23691, 0.00296, -14.07333], "size": [3, 2, 2], "pivot": [7.62971, 0.73754, -13.08688], "rotation": [0, 57.5, 12.5], "uv": [117, 52]},
						{"origin": [-0.84406, 0.2861, -11.41168], "size": [4, 3, 3], "pivot": [-0.409, 1.5361, -9.95929], "rotation": [0, -75, -5], "uv": [92, 87]},
						{"origin": [-3.00509, 0.15459, -12.84594], "size": [4, 2, 2], "pivot": [-1.00509, 1.15459, -11.84594], "rotation": [19.53564, -60.79235, -25.65925], "uv": [107, 92]},
						{"origin": [-3.92011, -0.4901, -16.38831], "size": [4, 1, 1], "pivot": [-1.92011, 0.5099, -15.38831], "rotation": [103.16126, -80.35299, -111.79452], "uv": [119, 33]},
						{"origin": [-8.85584, -0.00131, -10.37077], "size": [5, 1, 1], "pivot": [-4.6477, 0.72164, -9.6466], "rotation": [39.86596, -76.18643, -47.9502], "uv": [113, 17]},
						{"origin": [-4.4838, -0.05542, -11.09318], "size": [3, 2, 2], "pivot": [-4.6477, 0.72164, -9.6466], "rotation": [142.89187, -75.30507, -152.71368], "uv": [117, 47]},
						{"origin": [9.17742, -1.01094, 5.68449], "size": [5, 1, 2], "pivot": [14.17742, -0.51094, 6.93449], "rotation": [0, -35, 12.5], "uv": [31, 71]},
						{"origin": [13.81625, -1.15256, 6.77715], "size": [3, 1, 1], "pivot": [14.81625, -0.65256, 7.27715], "rotation": [0, -12.5, 12.5], "uv": [75, 75]}
					]
				},
				{
					"name": "drop",
					"parent": "flower",
					"pivot": [0.75, 43, -32],
					"cubes": [
						{"origin": [-0.25, 43, -33], "size": [2, 2, 2], "uv": [133, 24]}
					]
				}
			]
		}
	]
}