{
	"format_version": "1.12.0",
	"minecraft:geometry": [
		{
			"description": {
				"identifier": "geometry.unknown",
				"texture_width": 64,
				"texture_height": 64,
				"visible_bounds_width": 2,
				"visible_bounds_height": 4,
				"visible_bounds_offset": [0, 1, 0]
			},
			"bones": [
				{
					"name": "reapersscythe",
					"pivot": [-0.00572, 19.91827, -2.23666],
					"cubes": [
						{
							"origin": [-0.66803, 12.63541, -0.16781],
							"size": [1.33606, 1.71475, 1.28606],
							"uv": {
								"north": {"uv": [6, 32], "uv_size": [1.25, 1.75]},
								"east": {"uv": [9, 32], "uv_size": [1.25, 1.75]},
								"south": {"uv": [21, 32], "uv_size": [1.25, 1.75]},
								"west": {"uv": [27, 32], "uv_size": [1.25, 1.75]},
								"up": {"uv": [34, 0], "uv_size": [1.25, 1.25]},
								"down": {"uv": [34, 7.25], "uv_size": [1.25, -1.25]}
							}
						},
						{
							"origin": [-0.7, -14, -0.06781],
							"size": [1.4, 27.63541, 1.1],
							"uv": {
								"north": {"uv": [0, 0], "uv_size": [1.375, 27.625]},
								"east": {"uv": [6, 0], "uv_size": [1.125, 27.625]},
								"south": {"uv": [3, 0], "uv_size": [1.375, 27.625]},
								"west": {"uv": [9, 0], "uv_size": [1.125, 27.625]},
								"up": {"uv": [18, 34], "uv_size": [1.375, 1.125]},
								"down": {"uv": [34, 26.125], "uv_size": [1.375, -1.125]}
							}
						},
						{
							"origin": [-0.75, -14.75, -0.06781],
							"size": [1.5, 1.1, 1.1],
							"pivot": [-0.05, -14.2, 0.48219],
							"rotation": [-45, 0, 0],
							"uv": {
								"north": {"uv": [33, 19], "uv_size": [1.5, 1.125]},
								"east": {"uv": [0, 35], "uv_size": [1.125, 1.125]},
								"south": {"uv": [33, 22], "uv_size": [1.5, 1.125]},
								"west": {"uv": [3, 35], "uv_size": [1.125, 1.125]},
								"up": {"uv": [24, 33], "uv_size": [1.5, 1.125]},
								"down": {"uv": [33, 33.125], "uv_size": [1.5, -1.125]}
							}
						},
						{
							"origin": [-0.64303, 13.99253, -2.03306],
							"size": [1.28606, 1.28606, 3.00081],
							"pivot": [0, 19.50301, 1.23332],
							"rotation": [22.5, 0, 0],
							"uv": {
								"north": {"uv": [34, 9], "uv_size": [1.25, 1.25]},
								"east": {"uv": [25, 4], "uv_size": [3, 1.25]},
								"south": {"uv": [12, 34], "uv_size": [1.25, 1.25]},
								"west": {"uv": [21, 26], "uv_size": [3, 1.25]},
								"up": {"uv": [15, 26], "uv_size": [1.25, 3]},
								"down": {"uv": [25, 29], "uv_size": [1.25, -3]}
							}
						},
						{
							"origin": [-0.67688, 17.29828, 5.03349],
							"size": [1.35375, 3.15875, 1.35375],
							"pivot": [0, 19.77631, 1.13525],
							"rotation": [-45, 0, 0],
							"uv": {
								"north": {"uv": [18, 18], "uv_size": [1.375, 3.125]},
								"east": {"uv": [19, 3], "uv_size": [1.375, 3.125]},
								"south": {"uv": [12, 19], "uv_size": [1.375, 3.125]},
								"west": {"uv": [21, 8], "uv_size": [1.375, 3.125]},
								"up": {"uv": [30, 32], "uv_size": [1.375, 1.375]},
								"down": {"uv": [33, 14.375], "uv_size": [1.375, -1.375]}
							}
						},
						{
							"origin": [-0.7125, 18.49281, 4.87126],
							"size": [1.425, 2.375, 1.425],
							"pivot": [0, 19.94643, 0.91445],
							"rotation": [-22.5, 0, 0],
							"uv": {
								"north": {"uv": [27, 18], "uv_size": [1.375, 2.375]},
								"east": {"uv": [27, 22], "uv_size": [1.375, 2.375]},
								"south": {"uv": [28, 0], "uv_size": [1.375, 2.375]},
								"west": {"uv": [28, 7], "uv_size": [1.375, 2.375]},
								"up": {"uv": [15, 33], "uv_size": [1.375, 1.375]},
								"down": {"uv": [33, 17.375], "uv_size": [1.375, -1.375]}
							}
						},
						{
							"origin": [-0.75, 18.73815, 4.73919],
							"size": [1.5, 3.5, 1.5],
							"uv": {
								"north": {"uv": [12, 0], "uv_size": [1.5, 3.5]},
								"east": {"uv": [12, 5], "uv_size": [1.5, 3.5]},
								"south": {"uv": [12, 10], "uv_size": [1.5, 3.5]},
								"west": {"uv": [15, 0], "uv_size": [1.5, 3.5]},
								"up": {"uv": [31, 29], "uv_size": [1.5, 1.5]},
								"down": {"uv": [0, 33.5], "uv_size": [1.5, -1.5]}
							}
						},
						{
							"origin": [-0.7875, 19.80788, 5.1115],
							"size": [1.575, 2.625, 1.575],
							"pivot": [0, 19.89862, 0.35396],
							"rotation": [22.5, 0, 0],
							"uv": {
								"north": {"uv": [21, 13], "uv_size": [1.625, 2.625]},
								"east": {"uv": [21, 17], "uv_size": [1.625, 2.625]},
								"south": {"uv": [21, 21], "uv_size": [1.625, 2.625]},
								"west": {"uv": [22, 0], "uv_size": [1.625, 2.625]},
								"up": {"uv": [21, 29], "uv_size": [1.625, 1.625]},
								"down": {"uv": [28, 30.625], "uv_size": [1.625, -1.625]}
							}
						},
						{
							"origin": [-0.82687, 25.16798, -1.45772],
							"size": [1.65375, 1.65375, 1.65375],
							"pivot": [0, 19.66038, 0.10992],
							"rotation": [-45, 0, 0],
							"uv": {
								"north": {"uv": [30, 14], "uv_size": [1.625, 1.625]},
								"east": {"uv": [15, 30], "uv_size": [1.625, 1.625]},
								"south": {"uv": [30, 17], "uv_size": [1.625, 1.625]},
								"west": {"uv": [30, 20], "uv_size": [1.625, 1.625]},
								"up": {"uv": [30, 23], "uv_size": [1.625, 1.625]},
								"down": {"uv": [24, 31.625], "uv_size": [1.625, -1.625]}
							}
						},
						{
							"origin": [-0.83514, 24.84908, -0.49195],
							"size": [1.67029, 1.67029, 1.67029],
							"pivot": [0, 18.80495, 0.90197],
							"rotation": [-22.5, 0, 0],
							"uv": {
								"north": {"uv": [31, 0], "uv_size": [1.625, 1.625]},
								"east": {"uv": [31, 7], "uv_size": [1.625, 1.625]},
								"south": {"uv": [31, 10], "uv_size": [1.625, 1.625]},
								"west": {"uv": [12, 31], "uv_size": [1.625, 1.625]},
								"up": {"uv": [18, 31], "uv_size": [1.625, 1.625]},
								"down": {"uv": [31, 27.625], "uv_size": [1.625, -1.625]}
							}
						},
						{
							"origin": [-0.8769, 24.71177, -0.35666],
							"size": [1.7538, 1.7538, 2.923],
							"uv": {
								"north": {"uv": [28, 11], "uv_size": [1.75, 1.75]},
								"east": {"uv": [15, 5], "uv_size": [2.875, 1.75]},
								"south": {"uv": [12, 28], "uv_size": [1.75, 1.75]},
								"west": {"uv": [15, 8], "uv_size": [2.875, 1.75]},
								"up": {"uv": [15, 11], "uv_size": [1.75, 2.875]},
								"down": {"uv": [12, 17.875], "uv_size": [1.75, -2.875]}
							}
						},
						{
							"origin": [-0.86822, 24.94383, 0.1365],
							"size": [1.73644, 1.73644, 2.89406],
							"pivot": [0, 18.05856, 1.87662],
							"rotation": [22.5, 0, 0],
							"uv": {
								"north": {"uv": [28, 26], "uv_size": [1.75, 1.75]},
								"east": {"uv": [15, 15], "uv_size": [2.875, 1.75]},
								"south": {"uv": [0, 29], "uv_size": [1.75, 1.75]},
								"west": {"uv": [18, 0], "uv_size": [2.875, 1.75]},
								"up": {"uv": [18, 11], "uv_size": [1.75, 2.875]},
								"down": {"uv": [15, 20.875], "uv_size": [1.75, -2.875]}
							}
						},
						{
							"origin": [-0.86822, 23.26199, -4.47746],
							"size": [1.73644, 1.73644, 2.31525],
							"pivot": [0, 24.13021, -3.03043],
							"rotation": [45, 0, 0],
							"uv": {
								"north": {"uv": [3, 29], "uv_size": [1.75, 1.75]},
								"east": {"uv": [24, 8], "uv_size": [2.375, 1.75]},
								"south": {"uv": [29, 4], "uv_size": [1.75, 1.75]},
								"west": {"uv": [24, 11], "uv_size": [2.375, 1.75]},
								"up": {"uv": [18, 23], "uv_size": [1.75, 2.375]},
								"down": {"uv": [12, 26.375], "uv_size": [1.75, -2.375]}
							}
						},
						{
							"origin": [-0.38889, 21.25568, -5.91756],
							"size": [0.73644, 0.81525, 1.48644],
							"pivot": [-0.02067, 21.66331, -5.29934],
							"rotation": [22.5, 0, 0],
							"uv": {
								"north": {"uv": [35, 3], "uv_size": [0.75, 0.875]},
								"east": {"uv": [34, 28], "uv_size": [1.5, 0.875]},
								"south": {"uv": [6, 35], "uv_size": [0.75, 0.875]},
								"west": {"uv": [34, 30], "uv_size": [1.5, 0.875]},
								"up": {"uv": [19, 8], "uv_size": [0.75, 1.5]},
								"down": {"uv": [19, 16.5], "uv_size": [0.75, -1.5]}
							}
						},
						{
							"origin": [-0.34322, 22.00352, -4.87707],
							"size": [0.68644, 0.21525, 0.73644],
							"pivot": [-0.025, 21.81114, -4.88385],
							"rotation": [45, 0, 0],
							"uv": {
								"north": {"uv": [35, 3], "uv_size": [0.75, 0.875]},
								"east": {"uv": [34, 28], "uv_size": [1.5, 0.875]},
								"south": {"uv": [6, 35], "uv_size": [0.75, 0.875]},
								"west": {"uv": [34, 30], "uv_size": [1.5, 0.875]},
								"up": {"uv": [19, 8], "uv_size": [0.75, 1.5]},
								"down": {"uv": [19, 16.5], "uv_size": [0.75, -1.5]}
							}
						},
						{
							"origin": [-0.86822, 21.40568, -4.66756],
							"size": [1.73644, 2.31525, 1.73644],
							"uv": {
								"north": {"uv": [24, 14], "uv_size": [1.75, 2.375]},
								"east": {"uv": [24, 18], "uv_size": [1.75, 2.375]},
								"south": {"uv": [24, 22], "uv_size": [1.75, 2.375]},
								"west": {"uv": [25, 0], "uv_size": [1.75, 2.375]},
								"up": {"uv": [6, 29], "uv_size": [1.75, 1.75]},
								"down": {"uv": [9, 30.75], "uv_size": [1.75, -1.75]}
							}
						},
						{
							"origin": [-0.76822, 20.94043, -4.61756],
							"size": [0.23644, 0.30762, 0.23644],
							"uv": {
								"north": {"uv": [40, 18], "uv_size": [0.25, 0.25]},
								"east": {"uv": [40, 20], "uv_size": [0.25, 0.25]},
								"south": {"uv": [22, 40], "uv_size": [0.25, 0.25]},
								"west": {"uv": [40, 22], "uv_size": [0.25, 0.25]},
								"up": {"uv": [24, 40], "uv_size": [0.25, 0.25]},
								"down": {"uv": [40, 32.25], "uv_size": [0.25, -0.25]}
							}
						},
						{
							"origin": [-0.81822, 21.19806, -4.66756],
							"size": [0.33644, 0.20762, 0.33644],
							"uv": {
								"north": {"uv": [37, 4], "uv_size": [0.375, 0.25]},
								"east": {"uv": [6, 37], "uv_size": [0.375, 0.25]},
								"south": {"uv": [37, 6], "uv_size": [0.375, 0.25]},
								"west": {"uv": [8, 37], "uv_size": [0.375, 0.25]},
								"up": {"uv": [8, 35], "uv_size": [0.375, 0.375]},
								"down": {"uv": [10, 35.375], "uv_size": [0.375, -0.375]}
							}
						},
						{
							"origin": [-0.71822, 20.48281, -4.56756],
							"size": [0.13644, 0.55762, 0.13644],
							"uv": {
								"north": {"uv": [37, 40], "uv_size": [0.125, 0.5]},
								"east": {"uv": [39, 40], "uv_size": [0.125, 0.5]},
								"south": {"uv": [41, 0], "uv_size": [0.125, 0.5]},
								"west": {"uv": [41, 2], "uv_size": [0.125, 0.5]},
								"up": {"uv": [34, 43], "uv_size": [0.125, 0.125]},
								"down": {"uv": [43, 34.125], "uv_size": [0.125, -0.125]}
							}
						},
						{
							"origin": [-0.11822, 20.84043, -4.61756],
							"size": [0.23644, 0.30762, 0.23644],
							"uv": {
								"north": {"uv": [41, 4], "uv_size": [0.25, 0.25]},
								"east": {"uv": [6, 41], "uv_size": [0.25, 0.25]},
								"south": {"uv": [41, 6], "uv_size": [0.25, 0.25]},
								"west": {"uv": [8, 41], "uv_size": [0.25, 0.25]},
								"up": {"uv": [41, 8], "uv_size": [0.25, 0.25]},
								"down": {"uv": [10, 41.25], "uv_size": [0.25, -0.25]}
							}
						},
						{
							"origin": [-0.06822, 20.38281, -4.56756],
							"size": [0.13644, 0.65762, 0.13644],
							"uv": {
								"north": {"uv": [40, 12], "uv_size": [0.125, 0.625]},
								"east": {"uv": [14, 40], "uv_size": [0.125, 0.625]},
								"south": {"uv": [40, 14], "uv_size": [0.125, 0.625]},
								"west": {"uv": [40, 16], "uv_size": [0.125, 0.625]},
								"up": {"uv": [43, 36], "uv_size": [0.125, 0.125]},
								"down": {"uv": [43, 38.125], "uv_size": [0.125, -0.125]}
							}
						},
						{
							"origin": [-0.16822, 21.09806, -4.66756],
							"size": [0.33644, 0.30762, 0.33644],
							"uv": {
								"north": {"uv": [37, 8], "uv_size": [0.375, 0.25]},
								"east": {"uv": [10, 37], "uv_size": [0.375, 0.25]},
								"south": {"uv": [37, 10], "uv_size": [0.375, 0.25]},
								"west": {"uv": [12, 37], "uv_size": [0.375, 0.25]},
								"up": {"uv": [21, 35], "uv_size": [0.375, 0.375]},
								"down": {"uv": [27, 35.375], "uv_size": [0.375, -0.375]}
							}
						},
						{
							"origin": [0.51111, 20.84043, -4.61756],
							"size": [0.23644, 0.40762, 0.23644],
							"uv": {
								"north": {"uv": [17, 37], "uv_size": [0.25, 0.375]},
								"east": {"uv": [19, 37], "uv_size": [0.25, 0.375]},
								"south": {"uv": [21, 37], "uv_size": [0.25, 0.375]},
								"west": {"uv": [37, 24], "uv_size": [0.25, 0.375]},
								"up": {"uv": [41, 10], "uv_size": [0.25, 0.25]},
								"down": {"uv": [12, 41.25], "uv_size": [0.25, -0.25]}
							}
						},
						{
							"origin": [0.56111, 20.58281, -4.56756],
							"size": [0.13644, 0.45762, 0.13644],
							"uv": {
								"north": {"uv": [16, 41], "uv_size": [0.125, 0.5]},
								"east": {"uv": [18, 41], "uv_size": [0.125, 0.5]},
								"south": {"uv": [20, 41], "uv_size": [0.125, 0.5]},
								"west": {"uv": [41, 24], "uv_size": [0.125, 0.5]},
								"up": {"uv": [43, 40], "uv_size": [0.125, 0.125]},
								"down": {"uv": [0, 44.125], "uv_size": [0.125, -0.125]}
							}
						},
						{
							"origin": [0.46111, 21.19806, -4.66756],
							"size": [0.33644, 0.20762, 0.33644],
							"uv": {
								"north": {"uv": [37, 26], "uv_size": [0.375, 0.25]},
								"east": {"uv": [27, 37], "uv_size": [0.375, 0.25]},
								"south": {"uv": [37, 28], "uv_size": [0.375, 0.25]},
								"west": {"uv": [29, 37], "uv_size": [0.375, 0.25]},
								"up": {"uv": [29, 35], "uv_size": [0.375, 0.375]},
								"down": {"uv": [31, 35.375], "uv_size": [0.375, -0.375]}
							}
						},
						{
							"origin": [0.46111, 21.19806, -3.26756],
							"size": [0.33644, 0.20762, 0.33644],
							"uv": {
								"north": {"uv": [37, 30], "uv_size": [0.375, 0.25]},
								"east": {"uv": [31, 37], "uv_size": [0.375, 0.25]},
								"south": {"uv": [33, 37], "uv_size": [0.375, 0.25]},
								"west": {"uv": [37, 34], "uv_size": [0.375, 0.25]},
								"up": {"uv": [33, 35], "uv_size": [0.375, 0.375]},
								"down": {"uv": [35, 35.375], "uv_size": [0.375, -0.375]}
							}
						},
						{
							"origin": [0.51111, 20.84043, -3.21756],
							"size": [0.23644, 0.40762, 0.23644],
							"uv": {
								"north": {"uv": [35, 37], "uv_size": [0.25, 0.375]},
								"east": {"uv": [37, 36], "uv_size": [0.25, 0.375]},
								"south": {"uv": [0, 38], "uv_size": [0.25, 0.375]},
								"west": {"uv": [2, 38], "uv_size": [0.25, 0.375]},
								"up": {"uv": [26, 41], "uv_size": [0.25, 0.25]},
								"down": {"uv": [41, 26.25], "uv_size": [0.25, -0.25]}
							}
						},
						{
							"origin": [0.56111, 20.58281, -3.16756],
							"size": [0.13644, 0.45762, 0.13644],
							"uv": {
								"north": {"uv": [28, 41], "uv_size": [0.125, 0.5]},
								"east": {"uv": [41, 28], "uv_size": [0.125, 0.5]},
								"south": {"uv": [30, 41], "uv_size": [0.125, 0.5]},
								"west": {"uv": [41, 30], "uv_size": [0.125, 0.5]},
								"up": {"uv": [2, 44], "uv_size": [0.125, 0.125]},
								"down": {"uv": [4, 44.125], "uv_size": [0.125, -0.125]}
							}
						},
						{
							"origin": [-0.16822, 21.09806, -3.26756],
							"size": [0.33644, 0.30762, 0.33644],
							"uv": {
								"north": {"uv": [4, 38], "uv_size": [0.375, 0.25]},
								"east": {"uv": [38, 12], "uv_size": [0.375, 0.25]},
								"south": {"uv": [14, 38], "uv_size": [0.375, 0.25]},
								"west": {"uv": [38, 14], "uv_size": [0.375, 0.25]},
								"up": {"uv": [36, 12], "uv_size": [0.375, 0.375]},
								"down": {"uv": [36, 14.375], "uv_size": [0.375, -0.375]}
							}
						},
						{
							"origin": [-0.11822, 20.74043, -3.21756],
							"size": [0.23644, 0.40762, 0.23644],
							"uv": {
								"north": {"uv": [38, 16], "uv_size": [0.25, 0.375]},
								"east": {"uv": [38, 18], "uv_size": [0.25, 0.375]},
								"south": {"uv": [38, 20], "uv_size": [0.25, 0.375]},
								"west": {"uv": [38, 22], "uv_size": [0.25, 0.375]},
								"up": {"uv": [32, 41], "uv_size": [0.25, 0.25]},
								"down": {"uv": [34, 41.25], "uv_size": [0.25, -0.25]}
							}
						},
						{
							"origin": [-0.06822, 20.38281, -3.16756],
							"size": [0.13644, 0.45762, 0.13644],
							"uv": {
								"north": {"uv": [41, 34], "uv_size": [0.125, 0.5]},
								"east": {"uv": [41, 36], "uv_size": [0.125, 0.5]},
								"south": {"uv": [41, 38], "uv_size": [0.125, 0.5]},
								"west": {"uv": [41, 40], "uv_size": [0.125, 0.5]},
								"up": {"uv": [44, 12], "uv_size": [0.125, 0.125]},
								"down": {"uv": [14, 44.125], "uv_size": [0.125, -0.125]}
							}
						},
						{
							"origin": [-0.81822, 21.19806, -3.26756],
							"size": [0.33644, 0.20762, 0.33644],
							"uv": {
								"north": {"uv": [23, 38], "uv_size": [0.375, 0.25]},
								"east": {"uv": [25, 38], "uv_size": [0.375, 0.25]},
								"south": {"uv": [38, 32], "uv_size": [0.375, 0.25]},
								"west": {"uv": [37, 38], "uv_size": [0.375, 0.25]},
								"up": {"uv": [15, 36], "uv_size": [0.375, 0.375]},
								"down": {"uv": [36, 16.375], "uv_size": [0.375, -0.375]}
							}
						},
						{
							"origin": [-0.76822, 20.94043, -3.21756],
							"size": [0.23644, 0.30762, 0.23644],
							"uv": {
								"north": {"uv": [0, 42], "uv_size": [0.25, 0.25]},
								"east": {"uv": [2, 42], "uv_size": [0.25, 0.25]},
								"south": {"uv": [4, 42], "uv_size": [0.25, 0.25]},
								"west": {"uv": [42, 12], "uv_size": [0.25, 0.25]},
								"up": {"uv": [14, 42], "uv_size": [0.25, 0.25]},
								"down": {"uv": [42, 14.25], "uv_size": [0.25, -0.25]}
							}
						},
						{
							"origin": [-0.71822, 20.68281, -3.16756],
							"size": [0.13644, 0.35762, 0.13644],
							"uv": {
								"north": {"uv": [43, 28], "uv_size": [0.125, 0.375]},
								"east": {"uv": [30, 43], "uv_size": [0.125, 0.375]},
								"south": {"uv": [43, 30], "uv_size": [0.125, 0.375]},
								"west": {"uv": [32, 43], "uv_size": [0.125, 0.375]},
								"up": {"uv": [44, 14], "uv_size": [0.125, 0.125]},
								"down": {"uv": [44, 16.125], "uv_size": [0.125, -0.125]}
							}
						},
						{
							"origin": [-0.81822, 21.19806, -3.71756],
							"size": [0.33644, 0.20762, 0.33644],
							"uv": {
								"north": {"uv": [39, 0], "uv_size": [0.375, 0.25]},
								"east": {"uv": [39, 2], "uv_size": [0.375, 0.25]},
								"south": {"uv": [39, 4], "uv_size": [0.375, 0.25]},
								"west": {"uv": [6, 39], "uv_size": [0.375, 0.25]},
								"up": {"uv": [36, 18], "uv_size": [0.375, 0.375]},
								"down": {"uv": [36, 20.375], "uv_size": [0.375, -0.375]}
							}
						},
						{
							"origin": [-0.71822, 20.58281, -3.61756],
							"size": [0.13644, 0.45762, 0.13644],
							"uv": {
								"north": {"uv": [42, 16], "uv_size": [0.125, 0.5]},
								"east": {"uv": [42, 18], "uv_size": [0.125, 0.5]},
								"south": {"uv": [42, 20], "uv_size": [0.125, 0.5]},
								"west": {"uv": [22, 42], "uv_size": [0.125, 0.5]},
								"up": {"uv": [44, 18], "uv_size": [0.125, 0.125]},
								"down": {"uv": [44, 20.125], "uv_size": [0.125, -0.125]}
							}
						},
						{
							"origin": [-0.76822, 20.84043, -3.66756],
							"size": [0.23644, 0.40762, 0.23644],
							"uv": {
								"north": {"uv": [39, 6], "uv_size": [0.25, 0.375]},
								"east": {"uv": [8, 39], "uv_size": [0.25, 0.375]},
								"south": {"uv": [39, 8], "uv_size": [0.25, 0.375]},
								"west": {"uv": [10, 39], "uv_size": [0.25, 0.375]},
								"up": {"uv": [42, 22], "uv_size": [0.25, 0.25]},
								"down": {"uv": [24, 42.25], "uv_size": [0.25, -0.25]}
							}
						},
						{
							"origin": [-0.81822, 21.19806, -4.21756],
							"size": [0.33644, 0.20762, 0.33644],
							"uv": {
								"north": {"uv": [39, 10], "uv_size": [0.375, 0.25]},
								"east": {"uv": [12, 39], "uv_size": [0.375, 0.25]},
								"south": {"uv": [16, 39], "uv_size": [0.375, 0.25]},
								"west": {"uv": [18, 39], "uv_size": [0.375, 0.25]},
								"up": {"uv": [36, 22], "uv_size": [0.375, 0.375]},
								"down": {"uv": [23, 36.375], "uv_size": [0.375, -0.375]}
							}
						},
						{
							"origin": [-0.71822, 20.58281, -4.11756],
							"size": [0.13644, 0.45762, 0.13644],
							"uv": {
								"north": {"uv": [42, 32], "uv_size": [0.125, 0.5]},
								"east": {"uv": [36, 42], "uv_size": [0.125, 0.5]},
								"south": {"uv": [38, 42], "uv_size": [0.125, 0.5]},
								"west": {"uv": [40, 42], "uv_size": [0.125, 0.5]},
								"up": {"uv": [22, 44], "uv_size": [0.125, 0.125]},
								"down": {"uv": [44, 22.125], "uv_size": [0.125, -0.125]}
							}
						},
						{
							"origin": [-0.76822, 20.84043, -4.16756],
							"size": [0.23644, 0.40762, 0.23644],
							"uv": {
								"north": {"uv": [20, 39], "uv_size": [0.25, 0.375]},
								"east": {"uv": [39, 24], "uv_size": [0.25, 0.375]},
								"south": {"uv": [39, 26], "uv_size": [0.25, 0.375]},
								"west": {"uv": [27, 39], "uv_size": [0.25, 0.375]},
								"up": {"uv": [42, 42], "uv_size": [0.25, 0.25]},
								"down": {"uv": [43, 0.25], "uv_size": [0.25, -0.25]}
							}
						},
						{
							"origin": [0.46111, 21.19806, -3.71756],
							"size": [0.33644, 0.20762, 0.33644],
							"uv": {
								"north": {"uv": [39, 28], "uv_size": [0.375, 0.25]},
								"east": {"uv": [29, 39], "uv_size": [0.375, 0.25]},
								"south": {"uv": [39, 30], "uv_size": [0.375, 0.25]},
								"west": {"uv": [31, 39], "uv_size": [0.375, 0.25]},
								"up": {"uv": [25, 36], "uv_size": [0.375, 0.375]},
								"down": {"uv": [36, 32.375], "uv_size": [0.375, -0.375]}
							}
						},
						{
							"origin": [0.51111, 20.84043, -3.66756],
							"size": [0.23644, 0.40762, 0.23644],
							"uv": {
								"north": {"uv": [33, 39], "uv_size": [0.25, 0.375]},
								"east": {"uv": [39, 34], "uv_size": [0.25, 0.375]},
								"south": {"uv": [35, 39], "uv_size": [0.25, 0.375]},
								"west": {"uv": [39, 36], "uv_size": [0.25, 0.375]},
								"up": {"uv": [43, 2], "uv_size": [0.25, 0.25]},
								"down": {"uv": [43, 4.25], "uv_size": [0.25, -0.25]}
							}
						},
						{
							"origin": [0.56111, 20.58281, -3.61756],
							"size": [0.13644, 0.45762, 0.13644],
							"uv": {
								"north": {"uv": [6, 43], "uv_size": [0.125, 0.5]},
								"east": {"uv": [43, 6], "uv_size": [0.125, 0.5]},
								"south": {"uv": [8, 43], "uv_size": [0.125, 0.5]},
								"west": {"uv": [43, 8], "uv_size": [0.125, 0.5]},
								"up": {"uv": [24, 44], "uv_size": [0.125, 0.125]},
								"down": {"uv": [44, 32.125], "uv_size": [0.125, -0.125]}
							}
						},
						{
							"origin": [0.46111, 21.09806, -4.21756],
							"size": [0.33644, 0.30762, 0.33644],
							"uv": {
								"north": {"uv": [39, 38], "uv_size": [0.375, 0.25]},
								"east": {"uv": [0, 40], "uv_size": [0.375, 0.25]},
								"south": {"uv": [2, 40], "uv_size": [0.375, 0.25]},
								"west": {"uv": [4, 40], "uv_size": [0.375, 0.25]},
								"up": {"uv": [37, 0], "uv_size": [0.375, 0.375]},
								"down": {"uv": [37, 2.375], "uv_size": [0.375, -0.375]}
							}
						},
						{
							"origin": [0.51111, 20.84043, -4.16756],
							"size": [0.23644, 0.30762, 0.23644],
							"uv": {
								"north": {"uv": [10, 43], "uv_size": [0.25, 0.25]},
								"east": {"uv": [43, 10], "uv_size": [0.25, 0.25]},
								"south": {"uv": [12, 43], "uv_size": [0.25, 0.25]},
								"west": {"uv": [16, 43], "uv_size": [0.25, 0.25]},
								"up": {"uv": [18, 43], "uv_size": [0.25, 0.25]},
								"down": {"uv": [20, 43.25], "uv_size": [0.25, -0.25]}
							}
						},
						{
							"origin": [0.56111, 20.48281, -4.11756],
							"size": [0.13644, 0.55762, 0.13644],
							"uv": {
								"north": {"uv": [43, 24], "uv_size": [0.125, 0.5]},
								"east": {"uv": [26, 43], "uv_size": [0.125, 0.5]},
								"south": {"uv": [43, 26], "uv_size": [0.125, 0.5]},
								"west": {"uv": [28, 43], "uv_size": [0.125, 0.5]},
								"up": {"uv": [36, 44], "uv_size": [0.125, 0.125]},
								"down": {"uv": [38, 44.125], "uv_size": [0.125, -0.125]}
							}
						},
						{
							"origin": [-0.83928, 21.63721, -3.79934],
							"size": [1.67856, 2.66254, 1.33127],
							"pivot": [-0.26047, 23.14212, -2.93112],
							"rotation": [-22.5, 0, 0],
							"uv": {
								"north": {"uv": [22, 4], "uv_size": [1.625, 2.625]},
								"east": {"uv": [27, 14], "uv_size": [1.375, 2.625]},
								"south": {"uv": [15, 22], "uv_size": [1.625, 2.625]},
								"west": {"uv": [18, 27], "uv_size": [1.375, 2.625]},
								"up": {"uv": [3, 32], "uv_size": [1.625, 1.375]},
								"down": {"uv": [32, 4.375], "uv_size": [1.625, -1.375]}
							}
						}
					]
				}
			]
		}
	]
}