{
  "_fv": 66,
  "_type": "recipe",
  "definition": {
    "recipeType": "Crafting",
    "recipeRetstackSize": 1,
    "group": "",
    "cookingBookCategory": "MISC",
    "xpReward": 0.0,
    "cookingTime": 200,
    "craftingBookCategory": "MISC",
    "recipeShapeless": false,
    "recipeSlots": [
      {
        "value": "Blocks.WOOL#14"
      },
      {
        "value": "Blocks.WOOL#14"
      },
      {
        "value": "Blocks.WOOL#14"
      },
      {
        "value": "Blocks.WOOL#6"
      },
      {
        "value": ""
      },
      {
        "value": "Blocks.WOOL#6"
      },
      {
        "value": "Blocks.WOOL#14"
      },
      {
        "value": ""
      },
      {
        "value": "Blocks.WOOL#14"
      }
    ],
    "recipeReturnStack": {
      "value": "CUSTOM:BanArmorS2.legs"
    },
    "name": "ban_leggings_season_2_recipe",
    "namespace": "mod"
  }
}