{
  "_fv": 66,
  "_type": "projectile",
  "definition": {
    "projectileItem": {
      "value": "Blocks.AIR"
    },
    "showParticles": false,
    "actionSound": {
      "value": "entity.arrow.shoot"
    },
    "igniteFire": false,
    "power": 1.0,
    "damage": 5.0,
    "knockback": 5,
    "entityModel": "Modelbasquia_spear_enitiy",
    "customModelTexture": "basquia_spear.png",
    "onHitsEntity": {
      "name": "BasquiasProjectileProjectileHitsLivingEntity"
    },
    "onFlyingTick": {
      "name": "BasquiasProjectileWhileProjectileFlyingTick"
    }
  }
}