{
  "_fv": 66,
  "_type": "projectile",
  "definition": {
    "projectileItem": {
      "value": "Blocks.AIR"
    },
    "showParticles": false,
    "actionSound": {
      "value": ""
    },
    "igniteFire": false,
    "power": 1.0,
    "damage": 5.0,
    "knockback": 5,
    "entityModel": "ModelKiller_iceberg",
    "customModelTexture": "icelance.png",
    "onHitsEntity": {
      "name": "IceAnchorProjectileHitsLivingEntity"
    },
    "onFlyingTick": {
      "name": "IceAnchorWhileProjectileFlyingTick"
    }
  }
}