{
  "credit": "Made with Blockbench",
  "parent": "builtin/entity",
  "texture_size": [
    64,
    64
  ],
  "display": {
    "thirdperson_righthand": {
      "rotation": [
        162.98,
        84.62,
        -71.04
      ],
      "translation": [
        0.5,
        3,
        0
      ],
      "scale": [
        0.1,
        0.1,
        0.1
      ]
    },
    "thirdperson_lefthand": {
      "scale": [
        0.1,
        0.1,
        0.1
      ]
    },
    "firstperson_righthand": {
      "scale": [
        0.1,
        0.1,
        0.1
      ]
    },
    "firstperson_lefthand": {
      "scale": [
        0.1,
        0.1,
        0.1
      ]
    },
    "ground": {
      "scale": [
        0.1,
        0.1,
        0.1
      ]
    },
    "gui": {
      "scale": [
        0.1,
        0.1,
        0.1
      ]
    },
    "head": {
      "scale": [
        0.1,
        0.1,
        0.1
      ]
    },
    "fixed": {
      "scale": [
        0.1,
        0.1,
        0.1
      ]
    }
  },
  "textures": {
    "particle": "item/rhitta-texture"
  }
}